felis/__init__.py
felis/py.typed
felis-0.3.0.dist-info/METADATA
felis-0.3.0.dist-info/WHEEL
felis-0.3.0.dist-info/RECORD
