Metadata-Version: 2.3
Name: felis
Version: 0.3.0
Summary: Add your description here
Author-email: Yevgnen Koh <wherejoystarts@gmail.com>
Requires-Python: >=3.10.11
Requires-Dist: aisuite[all]>=0.1.6
Requires-Dist: httpx[socks]>=0.28.1
